docs/plugins/components/TestComponent.py
documentation/docs/gen_ref_pages.py
documentation/site/gen_ref_pages.py
examples/components/amazon.py
examples/components/azure_graph.py
examples/components/best_buy.py
examples/components/cnn.py
examples/components/company_scrapper.py
examples/components/costco.py
examples/components/costco_scrapper.py
examples/components/download_s3.py
examples/components/google_places.py
examples/components/lowes.py
examples/components/pokemon.py
examples/components/powerpoint.py
examples/components/qs.py
examples/components/rethink.py
examples/components/scrappage.py
examples/components/target.py
examples/components/test_notify.py
examples/components/test_tfilter.py
examples/components/walmart.py
examples/tests/test_o365.py
flowtask/__init__.py
flowtask/__main__.py
flowtask/_version.py
flowtask/conf.py
flowtask/download.py
flowtask/exceptions.c
flowtask/exceptions.cpython-312-x86_64-linux-gnu.so
flowtask/models.py
flowtask/runner.py
flowtask/tests.py
flowtask/version.py
flowtask/bots/__init__.py
flowtask/bots/check.py
flowtask/bots/codebot.py
flowtask/components/ASPX.py
flowtask/components/AddDataset.py
flowtask/components/Amazon.py
flowtask/components/AutoTask.py
flowtask/components/Azure.py
flowtask/components/AzureUsers.py
flowtask/components/BaseAction.py
flowtask/components/BaseLoop.py
flowtask/components/BestBuy.py
flowtask/components/CSVToGCS.py
flowtask/components/CallAnalysis.py
flowtask/components/CallSummary.py
flowtask/components/CopyTo.py
flowtask/components/CopyToBigQuery.py
flowtask/components/CopyToMongoDB.py
flowtask/components/CopyToPg.py
flowtask/components/CopyToRethink.py
flowtask/components/Costco.py
flowtask/components/CreateGCSBucket.py
flowtask/components/CustomerSatisfaction.py
flowtask/components/DataInput.py
flowtask/components/DateList.py
flowtask/components/DbClient.py
flowtask/components/DialPad.py
flowtask/components/DispatchMe.py
flowtask-5.9.38.dist-info/METADATA
flowtask-5.9.38.dist-info/WHEEL
flowtask-5.9.38.dist-info/entry_points.txt
flowtask-5.9.38.dist-info/top_level.txt
flowtask-5.9.38.dist-info/RECORD
flowtask-5.9.38.dist-info/licenses/LICENSE
