Metadata-Version: 2.4
Name: flowtask
Version: 5.9.38
Summary: Framework for Task orchestration
Author-email: Jesus Lara <jesuslarag@gmail.com>
License: Apache-2.0
Project-URL: Homepage, https://github.com/phenobarbital/flowtask
Project-URL: Source, https://github.com/phenobarbital/flowtask
Project-URL: Funding, https://paypal.me/phenobarbital
Project-URL: Say Thanks!, https://saythanks.io/to/phenobarbital
Keywords: Flowtask,Data Integration,Task Orchestration,Task-Runner,Pipelines
Classifier: Development Status :: 4 - Beta
Classifier: Intended Audience :: Developers
Classifier: Topic :: Software Development :: Libraries :: Application Frameworks
Classifier: Topic :: Software Development :: Libraries :: Python Modules
Classifier: Topic :: Software Development :: Build Tools
Classifier: Topic :: Utilities
Classifier: Programming Language :: Python :: 3.9
Classifier: Programming Language :: Python :: 3.10
Classifier: Programming Language :: Python :: 3.11
Classifier: Programming Language :: Python :: 3.12
Classifier: Programming Language :: Python :: 3.13
Classifier: License :: OSI Approved :: Apache Software License
Classifier: Framework :: AsyncIO
Requires-Python: >=3.10.1
License-File: LICENSE
Requires-Dist: borax==3.5.0
Requires-Dist: PyDrive==1.3.1
Requires-Dist: chardet==5.2.0
Requires-Dist: aiohttp-jinja2==1.6
Requires-Dist: asyncssh[bcrypt,fido2,libnacl,pkcs11,pyOpenSSL]>=2.18.0
Requires-Dist: pyxlsb==1.0.10
Requires-Dist: python-calamine==0.2.3
Requires-Dist: pyecharts==2.0.8
Requires-Dist: selenium>=4.35.0
Requires-Dist: snapshot-selenium==0.0.2
Requires-Dist: httpx[http2,socks]>=0.26.0
Requires-Dist: urllib3[socks]>=2.3.0
Requires-Dist: requests==2.32.4
Requires-Dist: h2>=4.2.0
Requires-Dist: blinker>=1.9.0
Requires-Dist: webdriver-manager==4.0.2
Requires-Dist: aioimaplib==1.1.0
Requires-Dist: adal==1.2.7
Requires-Dist: xlrd==2.0.1
Requires-Dist: xmltodict==1.0.2
Requires-Dist: zeep==4.3.1
Requires-Dist: nltk==3.9.1
Requires-Dist: jdcal==1.4.1
Requires-Dist: html5lib==1.1
Requires-Dist: shapely==2.0.6
Requires-Dist: tzwhere==3.0.3
Requires-Dist: tabulate==0.9.0
Requires-Dist: python-magic==0.4.27
Requires-Dist: pytomlpp==1.0.13
Requires-Dist: psutil==6.0.0
Requires-Dist: networkx>=3.4.1
Requires-Dist: gitpython==3.1.43
Requires-Dist: watchdog>=6.0.0
Requires-Dist: hachiko==0.4.0
Requires-Dist: paramiko==3.4.0
Requires-Dist: jira==3.10.5
Requires-Dist: datatable==1.1.0
Requires-Dist: imageio==2.37.0
Requires-Dist: decorator>=5.1.1
Requires-Dist: emoji==2.14.1
Requires-Dist: caio==0.9.24
Requires-Dist: Wand==0.6.13
Requires-Dist: pylibdmtx==0.1.10
Requires-Dist: aiofile>=3.9.0
Requires-Dist: filetype==1.2.0
Requires-Dist: proxylists>=0.14.0
Requires-Dist: aioftp==0.23.1
Requires-Dist: py7zr==0.22.0
Requires-Dist: rarfile==4.2
Requires-Dist: python-pptx==1.0.2
Requires-Dist: gspread==6.2.0
Requires-Dist: oauth2client>=4.1.3
Requires-Dist: google-auth>=2.35.0
Requires-Dist: google-cloud-language>=2.15.0
Requires-Dist: googlemaps==4.10.0
Requires-Dist: fastavro==1.9.7
Requires-Dist: pgpy==0.6.0
Requires-Dist: dropbox==12.0.2
Requires-Dist: dask-expr==1.1.13
Requires-Dist: jsonpath_ng==1.7.0
Requires-Dist: ortools<=9.14.6206,>=9.11.4210
Requires-Dist: gmqtt==0.7.0
Requires-Dist: selectorlib==0.16.0
Requires-Dist: playwright==1.52.0
Requires-Dist: fuzzywuzzy==0.18.0
Requires-Dist: praw==7.8.1
Requires-Dist: prawcore==2.4.0
Requires-Dist: osmnx==2.0.1
Requires-Dist: pyrosm==0.6.2
Requires-Dist: osmium==4.0.2
Requires-Dist: python-Levenshtein==0.26.1
Requires-Dist: undetected_chromedriver==3.5.5
Requires-Dist: duckduckgo-search==7.5.0
Requires-Dist: numba>=0.62.1
Requires-Dist: APScheduler<3.12.0,>=3.11.0
Requires-Dist: google-cloud-bigquery>=3.30.0
Requires-Dist: pyheif==0.8.0
Requires-Dist: filetype==1.2.0
Requires-Dist: exif==1.6.1
Requires-Dist: pillow-avif-plugin==1.5.2
Requires-Dist: pillow-heif==0.22.0
Requires-Dist: pgvector==0.4.1
Requires-Dist: proxylists>=0.14.0
Requires-Dist: async-notify[all]>=1.4.0
Requires-Dist: querysource>=3.17.0
Requires-Dist: asyncdb[all]>=2.11.7
Requires-Dist: navconfig[default,uvloop]>=1.7.13
Requires-Dist: navigator-auth>=0.15.8
Requires-Dist: navigator-api[locale,uvloop]>=2.12.22
Requires-Dist: ai-parrot[anthropic,google,groq,images,llms,openai]>=0.17.4
Requires-Dist: msal>=1.30.0
Requires-Dist: azure-core==1.35.0
Requires-Dist: azure-identity==1.20.0
Requires-Dist: microsoft-kiota-authentication-azure==1.9.6
Requires-Dist: msgraph-sdk==1.22.0
Provides-Extra: ai
Requires-Dist: ai-parrot[agents,anthropic,google,groq,loaders,openai,vectors]>=0.15.0; extra == "ai"
Provides-Extra: dev
Requires-Dist: pytest>=5.4.0; extra == "dev"
Requires-Dist: coverage; extra == "dev"
Requires-Dist: pytest-asyncio==0.23.8; extra == "dev"
Requires-Dist: pytest-xdist==3.3.1; extra == "dev"
Requires-Dist: pytest-assume==2.4.3; extra == "dev"
Dynamic: license-file
